cjkjust.py
cjkjust-0.1.4.dist-info/LICENSE
cjkjust-0.1.4.dist-info/METADATA
cjkjust-0.1.4.dist-info/WHEEL
cjkjust-0.1.4.dist-info/top_level.txt
cjkjust-0.1.4.dist-info/RECORD
