Metadata-Version: 2.1
Name: cjkjust
Version: 0.1.4
Summary: Having strings containing CJK characters left-, right-justified or centered conveniently.
Home-page: https://github.com/kkew3/cjkjust.git
Author: Kaiwen Wu
Author-email: kps6326@hotmail.com
License: MIT
Platform: UNKNOWN
Classifier: License :: OSI Approved :: MIT License
Classifier: Programming Language :: Python :: 2.7
Classifier: Programming Language :: Python :: 3
Requires-Python: >=2.7
License-File: LICENSE
Provides-Extra: allchars
Requires-Dist: wcwidth ; extra == 'allchars'
